ex_dstruct/__init__.py
ex_dstruct/linkedList.py
ex_dstruct-0.0.1.dist-info/METADATA
ex_dstruct-0.0.1.dist-info/WHEEL
ex_dstruct-0.0.1.dist-info/top_level.txt
ex_dstruct-0.0.1.dist-info/RECORD
