Metadata-Version: 2.1
Name: ex-dstruct
Version: 0.0.1
Summary: Used to add extra data types used in CS
Home-page: UNKNOWN
Author: Nitro Learn
Author-email: learn0855@gmail.com
License: UNKNOWN
Platform: UNKNOWN
Classifier: Programming Language :: Python :: 3
Classifier: License :: OSI Approved :: MIT License
Classifier: Operating System :: OS Independent
Requires-Python: >=3.5
